controltmux.py
controltmux/__init__.py
controltmux/__main__.py
controltmux/tmux-default-1.7.conf
controltmux/tmux-default-2.0.conf
controltmux/tmux.setup.sh
controltmux/usersetup.py
control_tmux-0.0.11.dist-info/LICENSE
control_tmux-0.0.11.dist-info/METADATA
control_tmux-0.0.11.dist-info/WHEEL
control_tmux-0.0.11.dist-info/entry_points.txt
control_tmux-0.0.11.dist-info/top_level.txt
control_tmux-0.0.11.dist-info/RECORD
