Metadata-Version: 2.1
Name: control-tmux
Version: 0.0.11
Summary: A wrapper around tmux allowing quick switching and session saving.
Home-page: https://ktpanda.org/software/control-tmux
Author: Katie Rust
Author-email: katie@ktpanda.org
License: MIT License
Classifier: Programming Language :: Python :: 3
Classifier: License :: OSI Approved :: MIT License
Classifier: Operating System :: POSIX
Requires-Python: >=3.6
License-File: LICENSE
Requires-Dist: argcomplete (>=2.0.0)
Requires-Dist: importlib-resources ; python_version < "3.9"
